[{
        "id": "59c0aa97.4c1fa4",
        "type": "function",
        "z": "a0be30da.c2f178",
        "name": "Emotion Recognition algorithmia",
        "func": "var algorithmia = global.get('algorithmia');\n\nvar client = algorithmia(\"simveB7okFMrXh8YPEzhL/npVkT1\");\n\ninput = {\n    \"image\": \"data:image/png;base64,\"+msg.payload,\n    \"numResults\": 7\n}\n\nclient.algo(\"deeplearning/EmotionRecognitionCNNMBP/0.1.2\").pipe(input).then(\n    function(output) {\n  if(output.error) return console.error(\"error: \" + output.error);\n  console.log(output.result);\n  node.send({payload:output.result});\n});",
        "outputs": 1,
        "noerr": 0,
        "x": 680,
        "y": 260,
        "wires": [
            [
                "41c98cef.dd2fbc",
                "b52d1cca.983e88"
            ]
        ]
    },
    {
        "id": "41c98cef.dd2fbc",
        "type": "debug",
        "z": "a0be30da.c2f178",
        "name": "",
        "active": true,
        "tosidebar": true,
        "console": false,
        "tostatus": false,
        "complete": "false",
        "x": 950,
        "y": 260,
        "wires": []
    },
    {
        "id": "22c55425.d64d5c",
        "type": "template",
        "z": "a0be30da.c2f178",
        "name": "",
        "field": "payload",
        "fieldType": "msg",
        "format": "handlebars",
        "syntax": "mustache",
        "template": "<img width=\"320px\" height=\"240px\" src=\"data:image/png;base64,{{{payload}}}\">",
        "output": "str",
        "x": 600,
        "y": 180,
        "wires": [
            [
                "67452c64.ff5a64"
            ]
        ]
    },
    {
        "id": "67452c64.ff5a64",
        "type": "ui_template",
        "z": "a0be30da.c2f178",
        "group": "cda7a1cc.ed4c3",
        "name": "Image",
        "order": 1,
        "width": "7",
        "height": "6",
        "format": "<div ng-bind-html=\"msg.payload\"></div>",
        "storeOutMessages": true,
        "fwdInMessages": true,
        "templateScope": "local",
        "x": 770,
        "y": 180,
        "wires": [
            []
        ]
    },
    {
        "id": "72367124.e5ab1",
        "type": "camera",
        "z": "a0be30da.c2f178",
        "name": "",
        "x": 210,
        "y": 180,
        "wires": [
            [
                "2901d702.764da8",
                "a2db5f4a.d7735"
            ]
        ]
    },
    {
        "id": "39ad1cae.7a60bc",
        "type": "debug",
        "z": "a0be30da.c2f178",
        "name": "",
        "active": true,
        "tosidebar": true,
        "console": false,
        "tostatus": false,
        "complete": "true",
        "x": 590,
        "y": 120,
        "wires": []
    },
    {
        "id": "b6b41165.70b778",
        "type": "debug",
        "z": "a0be30da.c2f178",
        "name": "",
        "active": true,
        "tosidebar": true,
        "console": false,
        "tostatus": false,
        "complete": "true",
        "x": 630,
        "y": 380,
        "wires": []
    },
    {
        "id": "2901d702.764da8",
        "type": "base64",
        "z": "a0be30da.c2f178",
        "name": "",
        "action": "",
        "property": "payload",
        "x": 380,
        "y": 180,
        "wires": [
            [
                "39ad1cae.7a60bc",
                "22c55425.d64d5c",
                "59c0aa97.4c1fa4"
            ]
        ]
    },
    {
        "id": "a2db5f4a.d7735",
        "type": "visual-recognition-v3",
        "z": "a0be30da.c2f178",
        "name": "",
        "vr-service-endpoint": "https://gateway.watsonplatform.net/visual-recognition/api",
        "image-feature": "detectFaces",
        "lang": "",
        "x": 410,
        "y": 380,
        "wires": [
            [
                "b6b41165.70b778",
                "fa0eab89.a6abe8"
            ]
        ]
    },
    {
        "id": "fa0eab89.a6abe8",
        "type": "ui_text",
        "z": "a0be30da.c2f178",
        "group": "cda7a1cc.ed4c3",
        "order": 2,
        "width": 0,
        "height": 0,
        "name": "",
        "label": "Gender",
        "format": "{{msg.result.images[0].faces[0].gender.gender}}",
        "layout": "row-spread",
        "x": 640,
        "y": 440,
        "wires": []
    },
    {
        "id": "b52d1cca.983e88",
        "type": "ui_text",
        "z": "a0be30da.c2f178",
        "group": "cda7a1cc.ed4c3",
        "order": 3,
        "width": 0,
        "height": 0,
        "name": "",
        "label": "Dominant Facial Emotional Expression",
        "format": "{{msg.payload.results[0][1]}}",
        "layout": "row-spread",
        "x": 1040,
        "y": 320,
        "wires": []
    },
    {
        "id": "7f3bc068.3746b8",
        "type": "inject",
        "z": "a0be30da.c2f178",
        "name": "",
        "topic": "",
        "payload": "[]",
        "payloadType": "json",
        "repeat": "",
        "crontab": "",
        "once": false,
        "onceDelay": 0.1,
        "x": 450,
        "y": 320,
        "wires": [
            [
                "67452c64.ff5a64",
                "b52d1cca.983e88",
                "fa0eab89.a6abe8"
            ]
        ]
    },
    {
        "id": "51ae54d.506a8ac",
        "type": "http request",
        "z": "a0be30da.c2f178",
        "name": "",
        "method": "POST",
        "ret": "obj",
        "url": "https://api-face.sightcorp.com/api/detect/",
        "tls": "",
        "x": 770,
        "y": 600,
        "wires": [
            [
                "37aa81ee.8bf50e"
            ]
        ]
    },
    {
        "id": "853497ac.58c958",
        "type": "inject",
        "z": "a0be30da.c2f178",
        "name": "",
        "topic": "",
        "payload": "",
        "payloadType": "date",
        "repeat": "",
        "crontab": "",
        "once": false,
        "x": 260,
        "y": 600,
        "wires": [
            [
                "260e30a6.b371f8"
            ]
        ]
    },
    {
        "id": "260e30a6.b371f8",
        "type": "function",
        "z": "a0be30da.c2f178",
        "name": "set payload and headers",
        "func": "msg.payload = {\"app_key\": \"e8fa8fe6c9f3466e8414f4793babefc2\", \"url\":\"http://www.naircare.co.uk/images/main/hub/bg-face.jpg\"};\n\nmsg.headers={\n    \"Content-Type\": \"application/x-www-form-urlencoded\"\n  }\n\nreturn msg;",
        "outputs": 1,
        "noerr": 0,
        "x": 530,
        "y": 600,
        "wires": [
            [
                "51ae54d.506a8ac"
            ]
        ]
    },
    {
        "id": "37aa81ee.8bf50e",
        "type": "debug",
        "z": "a0be30da.c2f178",
        "name": "",
        "active": true,
        "tosidebar": true,
        "console": false,
        "tostatus": false,
        "complete": "true",
        "x": 950,
        "y": 600,
        "wires": []
    },
    {
        "id": "cda7a1cc.ed4c3",
        "type": "ui_group",
        "z": "",
        "name": "Take a Photo!! :)",
        "tab": "c6f60837.2a74e8",
        "disp": true,
        "width": "7",
        "collapse": false
    },
    {
        "id": "c6f60837.2a74e8",
        "type": "ui_tab",
        "z": "",
        "name": "Home",
        "icon": "dashboard",
        "disabled": false,
        "hidden": false
    }
]